MANIFEST.in
setup.py
vakkenranking/__init__.py
vakkenranking/mapping.py
vakkenranking/parsing.py
vakkenranking/rendering.py
vakkenranking/statistics.py
vakkenranking.egg-info/PKG-INFO
vakkenranking.egg-info/SOURCES.txt
vakkenranking.egg-info/dependency_links.txt
vakkenranking.egg-info/entry_points.txt
vakkenranking.egg-info/requires.txt
vakkenranking.egg-info/top_level.txt
vakkenranking/templates/template.html