Metadata-Version: 1.0
Name: vakkenranking
Version: 0.2.0
Summary: Parser application for Radboud University course evaluations
Home-page: https://github.com/lscholten/vakkenranking
Author: Luuk Scholten
Author-email: info@luukscholten.com
License: MIT
Platform: UNKNOWN
